
{
  "header": {
    "reportVersion": 1,
    "event": "Allocation failed - JavaScript heap out of memory",
    "trigger": "FatalError",
    "filename": "report.20200302.132105.20688.0.001.json",
    "dumpEventTime": "2020-03-02T13:21:05Z",
    "dumpEventTimeStamp": "1583173265892",
    "processId": 20688,
    "cwd": "C:\\school\\SoftwareEngineering\\PMAP2020",
    "commandLine": [
      "node",
      "C:\\Users\\tavar\\AppData\\Roaming\\npm\\\\node_modules\\@angular\\cli\\bin\\ng",
      "serve"
    ],
    "nodejsVersion": "v12.16.0",
    "wordSize": 64,
    "arch": "x64",
    "platform": "win32",
    "componentVersions": {
      "node": "12.16.0",
      "v8": "7.8.279.23-node.31",
      "uv": "1.34.0",
      "zlib": "1.2.11",
      "brotli": "1.0.7",
      "ares": "1.15.0",
      "modules": "72",
      "nghttp2": "1.40.0",
      "napi": "5",
      "llhttp": "2.0.4",
      "http_parser": "2.9.3",
      "openssl": "1.1.1d",
      "cldr": "35.1",
      "icu": "64.2",
      "tz": "2019c",
      "unicode": "12.1"
    },
    "release": {
      "name": "node",
      "lts": "Erbium",
      "headersUrl": "https://nodejs.org/download/release/v12.16.0/node-v12.16.0-headers.tar.gz",
      "sourceUrl": "https://nodejs.org/download/release/v12.16.0/node-v12.16.0.tar.gz",
      "libUrl": "https://nodejs.org/download/release/v12.16.0/win-x64/node.lib"
    },
    "osName": "Windows_NT",
    "osRelease": "10.0.18362",
    "osVersion": "Windows 10 Home",
    "osMachine": "x86_64",
    "cpus": [
      {
        "model": "Intel(R) Core(TM) i7-7700HQ CPU @ 2.80GHz",
        "speed": 2808,
        "user": 2492062,
        "nice": 0,
        "sys": 4683640,
        "idle": 33948218,
        "irq": 2318109
      },
      {
        "model": "Intel(R) Core(TM) i7-7700HQ CPU @ 2.80GHz",
        "speed": 2808,
        "user": 1623296,
        "nice": 0,
        "sys": 1459000,
        "idle": 38041328,
        "irq": 388640
      },
      {
        "model": "Intel(R) Core(TM) i7-7700HQ CPU @ 2.80GHz",
        "speed": 2808,
        "user": 4095531,
        "nice": 0,
        "sys": 3038812,
        "idle": 33989281,
        "irq": 828687
      },
      {
        "model": "Intel(R) Core(TM) i7-7700HQ CPU @ 2.80GHz",
        "speed": 2808,
        "user": 2282281,
        "nice": 0,
        "sys": 2118546,
        "idle": 36722796,
        "irq": 685640
      },
      {
        "model": "Intel(R) Core(TM) i7-7700HQ CPU @ 2.80GHz",
        "speed": 2808,
        "user": 3240671,
        "nice": 0,
        "sys": 2800718,
        "idle": 35082234,
        "irq": 783062
      },
      {
        "model": "Intel(R) Core(TM) i7-7700HQ CPU @ 2.80GHz",
        "speed": 2808,
        "user": 2192062,
        "nice": 0,
        "sys": 2119546,
        "idle": 36812015,
        "irq": 331062
      },
      {
        "model": "Intel(R) Core(TM) i7-7700HQ CPU @ 2.80GHz",
        "speed": 2808,
        "user": 3305656,
        "nice": 0,
        "sys": 2237625,
        "idle": 35580343,
        "irq": 191953
      },
      {
        "model": "Intel(R) Core(TM) i7-7700HQ CPU @ 2.80GHz",
        "speed": 2808,
        "user": 2292031,
        "nice": 0,
        "sys": 2099078,
        "idle": 36732500,
        "irq": 433718
      }
    ],
    "networkInterfaces": [
      {
        "name": "Wi-Fi",
        "internal": false,
        "mac": "f8:34:41:fc:2a:51",
        "address": "fe80::3906:7005:d457:f237",
        "netmask": "ffff:ffff:ffff:ffff::",
        "family": "IPv6",
        "scopeid": 9
      },
      {
        "name": "Wi-Fi",
        "internal": false,
        "mac": "f8:34:41:fc:2a:51",
        "address": "10.200.26.52",
        "netmask": "255.255.192.0",
        "family": "IPv4"
      },
      {
        "name": "Loopback Pseudo-Interface 1",
        "internal": true,
        "mac": "00:00:00:00:00:00",
        "address": "::1",
        "netmask": "ffff:ffff:ffff:ffff:ffff:ffff:ffff:ffff",
        "family": "IPv6",
        "scopeid": 0
      },
      {
        "name": "Loopback Pseudo-Interface 1",
        "internal": true,
        "mac": "00:00:00:00:00:00",
        "address": "127.0.0.1",
        "netmask": "255.0.0.0",
        "family": "IPv4"
      }
    ],
    "host": "LAPTOP-86PN9P2E"
  },
  "javascriptStack": {
    "message": "No stack.",
    "stack": [
      "Unavailable."
    ]
  },
  "nativeStack": [
    {
      "pc": "0x00007ff6278019f9",
      "symbol": "std::basic_ostream<char,std::char_traits<char> >::operator<<+10873"
    },
    {
      "pc": "0x00007ff627805e1c",
      "symbol": "std::basic_ostream<char,std::char_traits<char> >::operator<<+28316"
    },
    {
      "pc": "0x00007ff627804dd8",
      "symbol": "std::basic_ostream<char,std::char_traits<char> >::operator<<+24152"
    },
    {
      "pc": "0x00007ff62790364b",
      "symbol": "v8::base::CPU::has_sse+38363"
    },
    {
      "pc": "0x00007ff62811a11e",
      "symbol": "v8::Isolate::ReportExternalAllocationLimitReached+94"
    },
    {
      "pc": "0x00007ff6281021f1",
      "symbol": "v8::SharedArrayBuffer::Externalize+833"
    },
    {
      "pc": "0x00007ff627fce74c",
      "symbol": "v8::internal::Heap::EphemeronKeyWriteBarrierFromCode+1436"
    },
    {
      "pc": "0x00007ff627fd99a0",
      "symbol": "v8::internal::Heap::ProtectUnprotectedMemoryChunks+1312"
    },
    {
      "pc": "0x00007ff627fd64c4",
      "symbol": "v8::internal::Heap::PageFlagsAreConsistent+3204"
    },
    {
      "pc": "0x00007ff627fcbce3",
      "symbol": "v8::internal::Heap::CollectGarbage+1283"
    },
    {
      "pc": "0x00007ff627fca354",
      "symbol": "v8::internal::Heap::AddRetainedMap+2452"
    },
    {
      "pc": "0x00007ff627feb53d",
      "symbol": "v8::internal::Factory::NewFillerObject+61"
    },
    {
      "pc": "0x00007ff627d50e21",
      "symbol": "v8::internal::interpreter::JumpTableTargetOffsets::iterator::operator=+1665"
    },
    {
      "pc": "0x00007ff628564fad",
      "symbol": "v8::internal::SetupIsolateDelegate::SetupHeap+546637"
    },
    {
      "pc": "0x00007ff6284e9533",
      "symbol": "v8::internal::SetupIsolateDelegate::SetupHeap+40147"
    },
    {
      "pc": "0x000001c4b8a37e18",
      "symbol": ""
    }
  ],
  "javascriptHeap": {
    "totalMemory": 2150928384,
    "totalCommittedMemory": 2150928384,
    "usedMemory": 2130443208,
    "availableMemory": 50781632,
    "memoryLimit": 2197815296,
    "heapSpaces": {
      "read_only_space": {
        "memorySize": 262144,
        "committedMemory": 262144,
        "capacity": 32808,
        "used": 32808,
        "available": 0
      },
      "new_space": {
        "memorySize": 4194304,
        "committedMemory": 4194304,
        "capacity": 2094912,
        "used": 338696,
        "available": 1756216
      },
      "old_space": {
        "memorySize": 2059288576,
        "committedMemory": 2059288576,
        "capacity": 2045599504,
        "used": 2045555912,
        "available": 43592
      },
      "code_space": {
        "memorySize": 3575808,
        "committedMemory": 3575808,
        "capacity": 3171424,
        "used": 3171424,
        "available": 0
      },
      "map_space": {
        "memorySize": 4460544,
        "committedMemory": 4460544,
        "capacity": 2631760,
        "used": 2631760,
        "available": 0
      },
      "large_object_space": {
        "memorySize": 78524416,
        "committedMemory": 78524416,
        "capacity": 78168320,
        "used": 78168320,
        "available": 0
      },
      "code_large_object_space": {
        "memorySize": 622592,
        "committedMemory": 622592,
        "capacity": 544288,
        "used": 544288,
        "available": 0
      },
      "new_large_object_space": {
        "memorySize": 0,
        "committedMemory": 0,
        "capacity": 2094912,
        "used": 0,
        "available": 2094912
      }
    }
  },
  "resourceUsage": {
    "userCpuSeconds": 379.671,
    "kernelCpuSeconds": 24.156,
    "cpuConsumptionPercent": 138.772,
    "maxRss": 2254794752,
    "pageFaults": {
      "IORequired": 1914874,
      "IONotRequired": 0
    },
    "fsActivity": {
      "reads": 6965,
      "writes": 387
    }
  },
  "libuv": [
  ],
  "environmentVariables": {
    "=::": "::\\",
    "=C:": "C:\\school\\SoftwareEngineering\\PMAP2020",
    "=ExitCode": "00000000",
    "ALLUSERSPROFILE": "C:\\ProgramData",
    "APPDATA": "C:\\Users\\tavar\\AppData\\Roaming",
    "BROWSERSLIST_IGNORE_OLD_DATA": "1",
    "ChocolateyInstall": "C:\\ProgramData\\chocolatey",
    "ChocolateyLastPathUpdate": "132255640322331495",
    "CLASSPATH": "C:\\Program Files\\Java\\javax.mail.jar;.",
    "CommonProgramFiles": "C:\\Program Files\\Common Files",
    "CommonProgramFiles(x86)": "C:\\Program Files (x86)\\Common Files",
    "CommonProgramW6432": "C:\\Program Files\\Common Files",
    "COMPUTERNAME": "LAPTOP-86PN9P2E",
    "ComSpec": "C:\\WINDOWS\\system32\\cmd.exe",
    "dp0": "C:\\Users\\tavar\\AppData\\Roaming\\npm\\",
    "DriverData": "C:\\Windows\\System32\\Drivers\\DriverData",
    "EQ_LIBRARY_PATH": "c:\\MinGW\\x86_64-w64-mingw32\\lib",
    "HOMEDRIVE": "C:",
    "HOMEPATH": "\\Users\\tavar",
    "LOCALAPPDATA": "C:\\Users\\tavar\\AppData\\Local",
    "LOGONSERVER": "\\\\LAPTOP-86PN9P2E",
    "MOZ_PLUGIN_PATH": "C:\\Program Files (x86)\\Foxit Software\\Foxit Reader\\plugins\\",
    "NUMBER_OF_PROCESSORS": "8",
    "OneDrive": "C:\\Users\\tavar\\OneDrive",
    "OneDriveConsumer": "C:\\Users\\tavar\\OneDrive",
    "OnlineServices": "Online Services",
    "OS": "Windows_NT",
    "Path": "C:\\Python27\\;C:\\Python27\\Scripts;C:\\Program Files (x86)\\Common Files\\Oracle\\Java\\javapath;C:\\Program Files (x86)\\Intel\\Intel(R) Management Engine Components\\iCLS\\;C:\\Program Files\\Intel\\Intel(R) Management Engine Components\\iCLS\\;c:\\MinGW\\bin;c:\\MinGW\\libexec\\gcc\\x86_64-w64-mingw32\\7.2.0;C:\\ProgramData\\Oracle\\Java\\javapath;C:\\windows\\system32;C:\\windows;C:\\windows\\System32\\Wbem;C:\\windows\\System32\\WindowsPowerShell\\v1.0\\;C:\\Program Files (x86)\\NVIDIA Corporation\\PhysX\\Common;C:\\WINDOWS\\system32;C:\\WINDOWS;C:\\WINDOWS\\System32\\Wbem;C:\\WINDOWS\\System32\\WindowsPowerShell\\v1.0\\;C:\\Program Files (x86)\\Intel\\Intel(R) Management Engine Components\\DAL;C:\\Program Files\\Intel\\Intel(R) Management Engine Components\\DAL;C:\\Program Files (x86)\\Intel\\Intel(R) Management Engine Components\\IPT;C:\\Program Files\\Intel\\Intel(R) Management Engine Components\\IPT;C:\\WINDOWS\\System32\\OpenSSH\\;C:\\Program Files\\NVIDIA Corporation\\NVIDIA NvDLISR;C:\\Program Files\\Intel\\WiFi\\bin\\;C:\\Program Files\\Common Files\\Intel\\WirelessCommon\\;C:\\WINDOWS\\system32;C:\\WINDOWS;C:\\WINDOWS\\System32\\Wbem;C:\\WINDOWS\\System32\\WindowsPowerShell\\v1.0\\;C:\\WINDOWS\\System32\\OpenSSH\\;C:\\ProgramData\\chocolatey\\bin;C:\\Program Files\\nodejs\\;C:\\Program Files\\Git\\cmd;C:\\Program Files\\Microsoft VS Code\\bin;C:\\Users\\tavar\\AppData\\Local\\Microsoft\\WindowsApps;C:\\Users\\tavar\\AppData\\Local\\atom\\bin;C:\\Users\\tavar\\AppData\\Roaming\\npm",
    "PATHEXT": ".COM;.EXE;.BAT;.CMD;.VBS;.VBE;.JSE;.WSF;.WSH;.MSC;.PY",
    "platformcode": "KV",
    "PROCESSOR_ARCHITECTURE": "AMD64",
    "PROCESSOR_IDENTIFIER": "Intel64 Family 6 Model 158 Stepping 9, GenuineIntel",
    "PROCESSOR_LEVEL": "6",
    "PROCESSOR_REVISION": "9e09",
    "ProgramData": "C:\\ProgramData",
    "ProgramFiles": "C:\\Program Files",
    "ProgramFiles(x86)": "C:\\Program Files (x86)",
    "ProgramW6432": "C:\\Program Files",
    "PROMPT": "$P$G",
    "PSModulePath": "C:\\Program Files\\WindowsPowerShell\\Modules;C:\\WINDOWS\\system32\\WindowsPowerShell\\v1.0\\Modules",
    "PUBLIC": "C:\\Users\\Public",
    "RegionCode": "NA",
    "SESSIONNAME": "Console",
    "SystemDrive": "C:",
    "SystemRoot": "C:\\WINDOWS",
    "TEMP": "C:\\Users\\tavar\\AppData\\Local\\Temp",
    "TMP": "C:\\Users\\tavar\\AppData\\Local\\Temp",
    "USERDOMAIN": "LAPTOP-86PN9P2E",
    "USERDOMAIN_ROAMINGPROFILE": "LAPTOP-86PN9P2E",
    "USERNAME": "tavar",
    "USERPROFILE": "C:\\Users\\tavar",
    "VBOX_MSI_INSTALL_PATH": "C:\\Program Files\\Oracle\\VirtualBox\\",
    "WEBPACK_DEV_SERVER": "true",
    "windir": "C:\\WINDOWS",
    "_prog": "node"
  },
  "sharedObjects": [
    "C:\\Program Files\\nodejs\\node.exe",
    "C:\\WINDOWS\\SYSTEM32\\ntdll.dll",
    "C:\\WINDOWS\\System32\\KERNEL32.DLL",
    "C:\\WINDOWS\\System32\\KERNELBASE.dll",
    "C:\\WINDOWS\\System32\\WS2_32.dll",
    "C:\\WINDOWS\\System32\\RPCRT4.dll",
    "C:\\WINDOWS\\SYSTEM32\\dbghelp.dll",
    "C:\\WINDOWS\\System32\\PSAPI.DLL",
    "C:\\WINDOWS\\System32\\ucrtbase.dll",
    "C:\\WINDOWS\\System32\\ADVAPI32.dll",
    "C:\\WINDOWS\\System32\\msvcrt.dll",
    "C:\\WINDOWS\\System32\\sechost.dll",
    "C:\\WINDOWS\\SYSTEM32\\USERENV.dll",
    "C:\\WINDOWS\\SYSTEM32\\IPHLPAPI.DLL",
    "C:\\WINDOWS\\System32\\profapi.dll",
    "C:\\WINDOWS\\System32\\USER32.dll",
    "C:\\WINDOWS\\System32\\win32u.dll",
    "C:\\WINDOWS\\System32\\GDI32.dll",
    "C:\\WINDOWS\\System32\\gdi32full.dll",
    "C:\\WINDOWS\\System32\\msvcp_win.dll",
    "C:\\WINDOWS\\System32\\CRYPT32.dll",
    "C:\\WINDOWS\\System32\\MSASN1.dll",
    "C:\\WINDOWS\\System32\\bcrypt.dll",
    "C:\\WINDOWS\\SYSTEM32\\WINMM.dll",
    "C:\\WINDOWS\\SYSTEM32\\winmmbase.dll",
    "C:\\WINDOWS\\System32\\cfgmgr32.dll",
    "C:\\WINDOWS\\System32\\bcryptPrimitives.dll",
    "C:\\WINDOWS\\System32\\IMM32.DLL",
    "C:\\WINDOWS\\System32\\powrprof.dll",
    "C:\\WINDOWS\\System32\\UMPDC.dll",
    "C:\\WINDOWS\\SYSTEM32\\CRYPTBASE.DLL",
    "C:\\WINDOWS\\system32\\uxtheme.dll",
    "C:\\WINDOWS\\System32\\combase.dll",
    "C:\\WINDOWS\\system32\\mswsock.dll",
    "C:\\WINDOWS\\System32\\kernel.appcore.dll",
    "C:\\WINDOWS\\System32\\NSI.dll",
    "C:\\WINDOWS\\SYSTEM32\\dhcpcsvc6.DLL",
    "C:\\WINDOWS\\SYSTEM32\\dhcpcsvc.DLL",
    "C:\\WINDOWS\\SYSTEM32\\DNSAPI.dll",
    "C:\\Windows\\System32\\rasadhlp.dll",
    "C:\\WINDOWS\\System32\\fwpuclnt.dll",
    "C:\\WINDOWS\\SYSTEM32\\ntmarta.dll",
    "C:\\WINDOWS\\system32\\napinsp.dll",
    "C:\\WINDOWS\\system32\\pnrpnsp.dll",
    "C:\\WINDOWS\\System32\\winrnr.dll",
    "C:\\WINDOWS\\system32\\NLAapi.dll",
    "C:\\WINDOWS\\system32\\wshbth.dll"
  ]
}